onesignal/__init__.py
onesignal/core.py
onesignal/device_notification.py
onesignal/errors.py
onesignal/filter.py
onesignal/filter_notification.py
onesignal/notification.py
onesignal/segment_notification.py
onesignal/utils.py
onesignal_notifications-0.2.6.dist-info/METADATA
onesignal_notifications-0.2.6.dist-info/RECORD
onesignal_notifications-0.2.6.dist-info/WHEEL
onesignal_notifications-0.2.6.dist-info/top_level.txt
