Metadata-Version: 2.1
Name: onesignal-notifications
Version: 0.2.6
Summary: OneSignal API Wrapper for Python
Home-page: https://github.com/Lanseuo/onesignal-notifications
Author: Lucas Hild
Author-email: contact@lucas-hild.de
License: MIT
Platform: UNKNOWN
Requires-Dist: requests
